age_mcp_server/__init__.py
age_mcp_server/server.py
mseep_age_mcp_server-0.2.25.dist-info/licenses/LICENSE
mseep_age_mcp_server-0.2.25.dist-info/METADATA
mseep_age_mcp_server-0.2.25.dist-info/WHEEL
mseep_age_mcp_server-0.2.25.dist-info/entry_points.txt
mseep_age_mcp_server-0.2.25.dist-info/top_level.txt
mseep_age_mcp_server-0.2.25.dist-info/RECORD
