Metadata-Version: 2.4
Name: mseep-age-mcp-server
Version: 0.2.25
Summary: Apache AGE MCP Server
Author-email: mseep <support@skydeck.ai>
License: MIT License
Project-URL: Homepage, https://github.com/rioriost/homebrew-age-mcp-server
Project-URL: Issues, https://github.com/rioriost/homebrew-age-mcp-server/issues
Requires-Python: >=3.13
License-File: LICENSE
Requires-Dist: agefreighter>=1.0.12
Requires-Dist: mcp>=1.13.1
Requires-Dist: ply>=3.11
Requires-Dist: psycopg[binary,pool]>=3.2.9
Dynamic: license-file
